[
    {
        "alt_media_url": null, 
        "can_delete_comments": false, 
        "can_view_comments": true, 
        "caption": {
            "created_time": "1492182961", 
            "from": {
                "full_name": "Tegar M K P", 
                "id": "3176222716", 
                "profile_picture": "https://instagram.fcgk4-2.fna.fbcdn.net/t51.2885-19/s150x150/14269253_198476207237335_1735316193_a.jpg", 
                "username": "tegarmkp"
            }, 
            "id": "17866616263099085", 
            "text": "Work hard; Play even harder #csgo"
        }, 
        "code": "BS3tXroANbc", 
        "comments": {
            "count": 2, 
            "data": [
                {
                    "created_time": "1492186028", 
                    "from": {
                        "full_name": "n rafiqua", 
                        "id": "40700791", 
                        "profile_picture": "https://instagram.fcgk4-2.fna.fbcdn.net/t51.2885-19/s150x150/12105234_1483045092000685_659961395_a.jpg", 
                        "username": "fiquaqua"
                    }, 
                    "id": "17853193309188472", 
                    "text": "Do me hardest :p"
                }, 
                {
                    "created_time": "1492186587", 
                    "from": {
                        "full_name": "", 
                        "id": "265218692", 
                        "profile_picture": "https://instagram.fcgk4-2.fna.fbcdn.net/t51.2885-19/s150x150/21147438_1767690879925390_8528038538397089792_a.jpg", 
                        "username": "ikikferdiansyah"
                    }, 
                    "id": "17856132292142512", 
                    "text": "mantap"
                }
            ]
        }, 
        "created_time": "1492182961", 
        "id": "1492861340979615452_3176222716", 
        "images": {
            "low_resolution": {
                "height": 320, 
                "url": "https://instagram.fcgk4-2.fna.fbcdn.net/t51.2885-15/s320x320/e35/17933746_1263280583789181_1500294697115975680_n.jpg", 
                "width": 320
            }, 
            "standard_resolution": {
                "height": 640, 
                "url": "https://instagram.fcgk4-2.fna.fbcdn.net/t51.2885-15/s640x640/sh0.08/e35/17933746_1263280583789181_1500294697115975680_n.jpg", 
                "width": 640
            }, 
            "thumbnail": {
                "height": 150, 
                "url": "https://instagram.fcgk4-2.fna.fbcdn.net/t51.2885-15/s150x150/e35/17933746_1263280583789181_1500294697115975680_n.jpg", 
                "width": 150
            }
        }, 
        "likes": {
            "count": 15, 
            "data": [
                {
                    "full_name": "", 
                    "id": "265218692", 
                    "profile_picture": "https://instagram.fcgk4-2.fna.fbcdn.net/t51.2885-19/s150x150/21147438_1767690879925390_8528038538397089792_a.jpg", 
                    "username": "ikikferdiansyah"
                }, 
                {
                    "full_name": "", 
                    "id": "574015780", 
                    "profile_picture": "https://instagram.fcgk4-2.fna.fbcdn.net/t51.2885-19/s150x150/20902434_111679872846433_3176169018797064192_a.jpg", 
                    "username": "melissadiagamoer"
                }, 
                {
                    "full_name": "Afifah Astarini", 
                    "id": "308481519", 
                    "profile_picture": "https://instagram.fcgk4-2.fna.fbcdn.net/t51.2885-19/s150x150/20066662_1408562392584987_1515066953662726144_a.jpg", 
                    "username": "_afifafif"
                }, 
                {
                    "full_name": "Andhika Dwi Juliansyah", 
                    "id": "428455382", 
                    "profile_picture": "https://instagram.fcgk4-2.fna.fbcdn.net/t51.2885-19/s150x150/18645572_1898551413736624_6657274771375390720_a.jpg", 
                    "username": "andhikadwij"
                }
            ]
        }, 
        "link": "https://www.instagram.com/p/BS3tXroANbc/", 
        "location": null, 
        "tags": [
            "csgo"
        ], 
        "type": "image", 
        "urls": [
            "https://instagram.fcgk4-2.fna.fbcdn.net/t51.2885-15/sh0.08/e35/17933746_1263280583789181_1500294697115975680_n.jpg"
        ], 
        "user": {
            "full_name": "Tegar M K P", 
            "id": "3176222716", 
            "profile_picture": "https://instagram.fcgk4-2.fna.fbcdn.net/t51.2885-19/s150x150/14269253_198476207237335_1735316193_a.jpg", 
            "username": "tegarmkp"
        }
    }, 
    {
        "alt_media_url": null, 
        "can_delete_comments": false, 
        "can_view_comments": true, 
        "caption": {
            "created_time": "1479665484", 
            "from": {
                "full_name": "Tegar M K P", 
                "id": "3176222716", 
                "profile_picture": "https://instagram.fcgk4-2.fna.fbcdn.net/t51.2885-19/s150x150/14269253_198476207237335_1735316193_a.jpg", 
                "username": "tegarmkp"
            }, 
            "id": "17844530773150021", 
            "text": "So blue~\n#sky #architecture"
        }, 
        "code": "BNCqLY7AJli", 
        "comments": {
            "count": 2, 
            "data": [
                {
                    "created_time": "1487820152", 
                    "from": {
                        "full_name": "n rafiqua", 
                        "id": "40700791", 
                        "profile_picture": "https://instagram.fcgk4-2.fna.fbcdn.net/t51.2885-19/s150x150/12105234_1483045092000685_659961395_a.jpg", 
                        "username": "fiquaqua"
                    }, 
                    "id": "17849778373180721", 
                    "text": "Tegar jorok"
                }, 
                {
                    "created_time": "1487820155", 
                    "from": {
                        "full_name": "n rafiqua", 
                        "id": "40700791", 
                        "profile_picture": "https://instagram.fcgk4-2.fna.fbcdn.net/t51.2885-19/s150x150/12105234_1483045092000685_659961395_a.jpg", 
                        "username": "fiquaqua"
                    }, 
                    "id": "17862600415099449", 
                    "text": "Mandi dong"
                }
            ]
        }, 
        "created_time": "1479665484", 
        "id": "1387857135810943330_3176222716", 
        "images": {
            "low_resolution": {
                "height": 320, 
                "url": "https://instagram.fcgk4-2.fna.fbcdn.net/t51.2885-15/s320x320/e35/15099434_137437796732698_6486857856413859840_n.jpg", 
                "width": 320
            }, 
            "standard_resolution": {
                "height": 640, 
                "url": "https://instagram.fcgk4-2.fna.fbcdn.net/t51.2885-15/s640x640/sh0.08/e35/15099434_137437796732698_6486857856413859840_n.jpg", 
                "width": 640
            }, 
            "thumbnail": {
                "height": 150, 
                "url": "https://instagram.fcgk4-2.fna.fbcdn.net/t51.2885-15/s150x150/e35/15099434_137437796732698_6486857856413859840_n.jpg", 
                "width": 150
            }
        }, 
        "likes": {
            "count": 27, 
            "data": [
                {
                    "full_name": "JAN PRENGEL", 
                    "id": "1518825213", 
                    "profile_picture": "https://instagram.fcgk4-2.fna.fbcdn.net/t51.2885-19/s150x150/17663482_1357326457658803_7858604294029705216_a.jpg", 
                    "username": "janprengel"
                }, 
                {
                    "full_name": "Stephen", 
                    "id": "565483748", 
                    "profile_picture": "https://instagram.fcgk4-2.fna.fbcdn.net/t51.2885-19/10950559_392415117594916_954147046_a.jpg", 
                    "username": "st.ph.n"
                }, 
                {
                    "full_name": "BerlinDoors", 
                    "id": "2269972955", 
                    "profile_picture": "https://instagram.fcgk4-2.fna.fbcdn.net/t51.2885-19/s150x150/18879330_1876506562673074_462879049375547392_a.jpg", 
                    "username": "berlindoors"
                }, 
                {
                    "full_name": "Charlotte S", 
                    "id": "3416250275", 
                    "profile_picture": "https://instagram.fcgk4-2.fna.fbcdn.net/t51.2885-19/s150x150/21433739_777441745775941_6033253406661935104_a.jpg", 
                    "username": "charlottesvisuals.hlplus"
                }
            ]
        }, 
        "link": "https://www.instagram.com/p/BNCqLY7AJli/", 
        "location": null, 
        "tags": [
            "sky", 
            "architecture"
        ], 
        "type": "image", 
        "urls": [
            "https://instagram.fcgk4-2.fna.fbcdn.net/t51.2885-15/sh0.08/e35/15099434_137437796732698_6486857856413859840_n.jpg"
        ], 
        "user": {
            "full_name": "Tegar M K P", 
            "id": "3176222716", 
            "profile_picture": "https://instagram.fcgk4-2.fna.fbcdn.net/t51.2885-19/s150x150/14269253_198476207237335_1735316193_a.jpg", 
            "username": "tegarmkp"
        }
    }, 
    {
        "alt_media_url": null, 
        "can_delete_comments": false, 
        "can_view_comments": true, 
        "caption": {
            "created_time": "1479567414", 
            "from": {
                "full_name": "Tegar M K P", 
                "id": "3176222716", 
                "profile_picture": "https://instagram.fcgk4-2.fna.fbcdn.net/t51.2885-19/s150x150/14269253_198476207237335_1735316193_a.jpg", 
                "username": "tegarmkp"
            }, 
            "id": "17864894530035212", 
            "text": "Random view from cisitu, cropped, edited\n#cloud #landscape"
        }, 
        "code": "BM_vH87A6xg", 
        "comments": {
            "count": 2, 
            "data": [
                {
                    "created_time": "1479567542", 
                    "from": {
                        "full_name": "Chris Eric Bratland", 
                        "id": "192239812", 
                        "profile_picture": "https://instagram.fcgk4-2.fna.fbcdn.net/t51.2885-19/s150x150/14718289_944063412366706_2955490790219972608_a.jpg", 
                        "username": "wilderness__stories"
                    }, 
                    "id": "17844513523157851", 
                    "text": "good job!!"
                }, 
                {
                    "created_time": "1479570755", 
                    "from": {
                        "full_name": "Cloud Nine Collection", 
                        "id": "2228713905", 
                        "profile_picture": "https://instagram.fcgk4-2.fna.fbcdn.net/t51.2885-19/s150x150/20479223_370552056695696_9178562849214038016_a.jpg", 
                        "username": "cloudninecollection"
                    }, 
                    "id": "17857376773078688", 
                    "text": "🙏"
                }
            ]
        }, 
        "created_time": "1479567414", 
        "id": "1387034464890367072_3176222716", 
        "images": {
            "low_resolution": {
                "height": 180, 
                "url": "https://instagram.fcgk4-2.fna.fbcdn.net/t51.2885-15/s320x320/e35/14262872_564586277072904_2683743944499527680_n.jpg", 
                "width": 320
            }, 
            "standard_resolution": {
                "height": 360, 
                "url": "https://instagram.fcgk4-2.fna.fbcdn.net/t51.2885-15/s640x640/sh0.08/e35/14262872_564586277072904_2683743944499527680_n.jpg", 
                "width": 640
            }, 
            "thumbnail": {
                "height": 150, 
                "url": "https://instagram.fcgk4-2.fna.fbcdn.net/t51.2885-15/s150x150/e35/c236.0.608.608/14262872_564586277072904_2683743944499527680_n.jpg", 
                "width": 150
            }
        }, 
        "likes": {
            "count": 21, 
            "data": [
                {
                    "full_name": "M. Alif Akbar Pranagara, S.H.", 
                    "id": "1069259336", 
                    "profile_picture": "https://instagram.fcgk4-2.fna.fbcdn.net/t51.2885-19/s150x150/16585737_186808575138998_4603578936943706112_a.jpg", 
                    "username": "pranagara1"
                }, 
                {
                    "full_name": "ＤＡＮＩ❁", 
                    "id": "1229027664", 
                    "profile_picture": "https://instagram.fcgk4-2.fna.fbcdn.net/t51.2885-19/s150x150/16465040_734610323371846_5584298220353224704_a.jpg", 
                    "username": "dani__code"
                }, 
                {
                    "full_name": "Park", 
                    "id": "237093008", 
                    "profile_picture": "https://instagram.fcgk4-2.fna.fbcdn.net/t51.2885-19/10665632_1475522789394561_51474862_a.jpg", 
                    "username": "vs_park"
                }, 
                {
                    "full_name": "", 
                    "id": "2877295898", 
                    "profile_picture": "https://instagram.fcgk4-2.fna.fbcdn.net/t51.2885-19/s150x150/18646474_329683110782397_8698953338852474880_a.jpg", 
                    "username": "ip_megan_"
                }
            ]
        }, 
        "link": "https://www.instagram.com/p/BM_vH87A6xg/", 
        "location": {
            "name": "Cisitu Lama XI"
        }, 
        "tags": [
            "cloud", 
            "landscape"
        ], 
        "type": "image", 
        "urls": [
            "https://instagram.fcgk4-2.fna.fbcdn.net/t51.2885-15/sh0.08/e35/14262872_564586277072904_2683743944499527680_n.jpg"
        ], 
        "user": {
            "full_name": "Tegar M K P", 
            "id": "3176222716", 
            "profile_picture": "https://instagram.fcgk4-2.fna.fbcdn.net/t51.2885-19/s150x150/14269253_198476207237335_1735316193_a.jpg", 
            "username": "tegarmkp"
        }
    }, 
    {
        "alt_media_url": "https://instagram.fcgk4-2.fna.fbcdn.net/t50.2886-16/14586963_950249255103992_1120778381680443392_n.mp4", 
        "can_delete_comments": false, 
        "can_view_comments": true, 
        "caption": {
            "created_time": "1475563081", 
            "from": {
                "full_name": "Tegar M K P", 
                "id": "3176222716", 
                "profile_picture": "https://instagram.fcgk4-2.fna.fbcdn.net/t51.2885-19/s150x150/14269253_198476207237335_1735316193_a.jpg", 
                "username": "tegarmkp"
            }, 
            "id": "17862896785010642", 
            "text": "soundcloud.com/tegarmkp/twilight-kotaro-oshio"
        }, 
        "code": "BLIZdwnguqY", 
        "comments": {
            "count": 1, 
            "data": [
                {
                    "created_time": "1485533506", 
                    "from": {
                        "full_name": "ICHA🍒", 
                        "id": "1344984207", 
                        "profile_picture": "https://instagram.fcgk4-2.fna.fbcdn.net/t51.2885-19/s150x150/21227477_118497455452992_3228618613954969600_a.jpg", 
                        "username": "diwaniristy"
                    }, 
                    "id": "17849449558141992", 
                    "text": "Follback:( @tegarmkp"
                }
            ]
        }, 
        "created_time": "1475563081", 
        "id": "1353443684254935704_3176222716", 
        "images": {
            "low_resolution": {
                "height": 320, 
                "url": "https://instagram.fcgk4-2.fna.fbcdn.net/t51.2885-15/s320x320/e15/14350910_1265300080169361_1121014085190680576_n.jpg", 
                "width": 320
            }, 
            "standard_resolution": {
                "height": 640, 
                "url": "https://instagram.fcgk4-2.fna.fbcdn.net/t51.2885-15/e15/14350910_1265300080169361_1121014085190680576_n.jpg", 
                "width": 640
            }, 
            "thumbnail": {
                "height": 150, 
                "url": "https://instagram.fcgk4-2.fna.fbcdn.net/t51.2885-15/s150x150/e15/14350910_1265300080169361_1121014085190680576_n.jpg", 
                "width": 150
            }
        }, 
        "likes": {
            "count": 11, 
            "data": [
                {
                    "full_name": "Afifah Astarini", 
                    "id": "308481519", 
                    "profile_picture": "https://instagram.fcgk4-2.fna.fbcdn.net/t51.2885-19/s150x150/20066662_1408562392584987_1515066953662726144_a.jpg", 
                    "username": "_afifafif"
                }, 
                {
                    "full_name": "Tarisha Raddin/Mind Illusions", 
                    "id": "304466079", 
                    "profile_picture": "https://instagram.fcgk4-2.fna.fbcdn.net/t51.2885-19/s150x150/14072972_1100135436737866_1078946233_a.jpg", 
                    "username": "raddintrwp"
                }, 
                {
                    "full_name": "M. Alif Akbar Pranagara, S.H.", 
                    "id": "1069259336", 
                    "profile_picture": "https://instagram.fcgk4-2.fna.fbcdn.net/t51.2885-19/s150x150/16585737_186808575138998_4603578936943706112_a.jpg", 
                    "username": "pranagara1"
                }, 
                {
                    "full_name": "", 
                    "id": "265218692", 
                    "profile_picture": "https://instagram.fcgk4-2.fna.fbcdn.net/t51.2885-19/s150x150/21147438_1767690879925390_8528038538397089792_a.jpg", 
                    "username": "ikikferdiansyah"
                }
            ]
        }, 
        "link": "https://www.instagram.com/p/BLIZdwnguqY/", 
        "location": null, 
        "tags": [], 
        "type": "video", 
        "urls": [
            "https://instagram.fcgk4-2.fna.fbcdn.net/t50.2886-16/14586963_950249255103992_1120778381680443392_n.mp4"
        ], 
        "user": {
            "full_name": "Tegar M K P", 
            "id": "3176222716", 
            "profile_picture": "https://instagram.fcgk4-2.fna.fbcdn.net/t51.2885-19/s150x150/14269253_198476207237335_1735316193_a.jpg", 
            "username": "tegarmkp"
        }, 
        "video_views": 73, 
        "videos": {
            "low_bandwidth": {
                "height": 480, 
                "url": "https://instagram.fcgk4-2.fna.fbcdn.net/t50.2886-16/14602933_1120407998039578_5451407465448996864_n.mp4", 
                "width": 480
            }, 
            "low_resolution": {
                "height": 480, 
                "url": "https://instagram.fcgk4-2.fna.fbcdn.net/t50.2886-16/14602933_1120407998039578_5451407465448996864_n.mp4", 
                "width": 480
            }, 
            "standard_resolution": {
                "height": 640, 
                "url": "https://instagram.fcgk4-2.fna.fbcdn.net/t50.2886-16/14586963_950249255103992_1120778381680443392_n.mp4", 
                "width": 640
            }
        }
    }, 
    {
        "alt_media_url": null, 
        "can_delete_comments": false, 
        "can_view_comments": true, 
        "caption": {
            "created_time": "1468587355", 
            "from": {
                "full_name": "Tegar M K P", 
                "id": "3176222716", 
                "profile_picture": "https://instagram.fcgk4-2.fna.fbcdn.net/t51.2885-19/s150x150/14269253_198476207237335_1735316193_a.jpg", 
                "username": "tegarmkp"
            }, 
            "id": "17858756455001809", 
            "text": "The sound coming out from this small guitar is unreal. Big and rich, easily overwhelm other full sized guitar in the shop. And the Koa wood's grain is so gergeous that this phone's camera couldn't fully capture its beauty.\n\n#taylorguitar #gsminikoa"
        }, 
        "code": "BH4gUqNDdGg", 
        "comments": {
            "count": 4, 
            "data": [
                {
                    "created_time": "1468590300", 
                    "from": {
                        "full_name": "Muthiah Salsabila", 
                        "id": "277494230", 
                        "profile_picture": "https://instagram.fcgk4-2.fna.fbcdn.net/t51.2885-19/s150x150/21294698_1471166162978870_6960769615915909120_a.jpg", 
                        "username": "muthiahsalsa"
                    }, 
                    "id": "17858758840001809", 
                    "text": "Ngeri bgt sis"
                }, 
                {
                    "created_time": "1468610231", 
                    "from": {
                        "full_name": "Tegar M K P", 
                        "id": "3176222716", 
                        "profile_picture": "https://instagram.fcgk4-2.fna.fbcdn.net/t51.2885-19/s150x150/14269253_198476207237335_1735316193_a.jpg", 
                        "username": "tegarmkp"
                    }, 
                    "id": "17858768125001809", 
                    "text": "@cekmuth lebih ngeri yang ke turki lah sis"
                }, 
                {
                    "created_time": "1468610309", 
                    "from": {
                        "full_name": "Tegar M K P", 
                        "id": "3176222716", 
                        "profile_picture": "https://instagram.fcgk4-2.fna.fbcdn.net/t51.2885-19/s150x150/14269253_198476207237335_1735316193_a.jpg", 
                        "username": "tegarmkp"
                    }, 
                    "id": "17858768149001809", 
                    "text": "@mardianineni Knp? Pengen denger?"
                }, 
                {
                    "created_time": "1471605585", 
                    "from": {
                        "full_name": "SophiaZeng", 
                        "id": "1132564494", 
                        "profile_picture": "https://instagram.fcgk4-2.fna.fbcdn.net/t51.2885-19/s150x150/17332614_288869264868378_820690382508523520_a.jpg", 
                        "username": "sophia_zxw"
                    }, 
                    "id": "17860816933001809", 
                    "text": "like"
                }
            ]
        }, 
        "created_time": "1468587355", 
        "id": "1294927050063073696_3176222716", 
        "images": {
            "low_resolution": {
                "height": 320, 
                "url": "https://instagram.fcgk4-2.fna.fbcdn.net/t51.2885-15/s320x320/e35/13741009_1734865543460963_597635793_n.jpg", 
                "width": 320
            }, 
            "standard_resolution": {
                "height": 640, 
                "url": "https://instagram.fcgk4-2.fna.fbcdn.net/t51.2885-15/s640x640/sh0.08/e35/13741009_1734865543460963_597635793_n.jpg", 
                "width": 640
            }, 
            "thumbnail": {
                "height": 150, 
                "url": "https://instagram.fcgk4-2.fna.fbcdn.net/t51.2885-15/s150x150/e35/13741009_1734865543460963_597635793_n.jpg", 
                "width": 150
            }
        }, 
        "likes": {
            "count": 29, 
            "data": [
                {
                    "full_name": "Friska Amalia", 
                    "id": "296790649", 
                    "profile_picture": "https://instagram.fcgk4-2.fna.fbcdn.net/t51.2885-19/s150x150/12070880_1512770432367389_953678319_a.jpg", 
                    "username": "friskamalia"
                }, 
                {
                    "full_name": "Arta Kusuma Ningtyas", 
                    "id": "190484452", 
                    "profile_picture": "https://instagram.fcgk4-2.fna.fbcdn.net/t51.2885-19/s150x150/20905177_1705473726424401_4635363589014683648_a.jpg", 
                    "username": "artatyas"
                }, 
                {
                    "full_name": "Mr. Aab 🇲🇨", 
                    "id": "269320710", 
                    "profile_picture": "https://instagram.fcgk4-2.fna.fbcdn.net/t51.2885-19/s150x150/20969340_352643375155804_5229574187022024704_a.jpg", 
                    "username": "aababdaf"
                }
            ]
        }, 
        "link": "https://www.instagram.com/p/BH4gUqNDdGg/", 
        "location": null, 
        "tags": [
            "taylorguitar", 
            "gsminikoa"
        ], 
        "type": "image", 
        "urls": [
            "https://instagram.fcgk4-2.fna.fbcdn.net/t51.2885-15/sh0.08/e35/13741009_1734865543460963_597635793_n.jpg"
        ], 
        "user": {
            "full_name": "Tegar M K P", 
            "id": "3176222716", 
            "profile_picture": "https://instagram.fcgk4-2.fna.fbcdn.net/t51.2885-19/s150x150/14269253_198476207237335_1735316193_a.jpg", 
            "username": "tegarmkp"
        }
    }, 
    {
        "alt_media_url": null, 
        "can_delete_comments": false, 
        "can_view_comments": true, 
        "caption": {
            "created_time": "1463153791", 
            "from": {
                "full_name": "Tegar M K P", 
                "id": "3176222716", 
                "profile_picture": "https://instagram.fcgk4-2.fna.fbcdn.net/t51.2885-19/s150x150/14269253_198476207237335_1735316193_a.jpg", 
                "username": "tegarmkp"
            }, 
            "id": "17856911407046320", 
            "text": "Bingung mau minum apa disini (Paskal Food Market)? Minum aja nih Teh Poci. Dengan 13,5k IDR kamu bisa dapet teh poci yang sesungguhny. Dedaunan teh pilihan dan gula batu diseduh di Poci beneran menghasilkan cita rasa dan aroma teh yang mantap (inget ini cuma 13,5k IDR)."
        }, 
        "code": "BFWkn0qqnZd", 
        "comments": {
            "count": 5, 
            "data": [
                {
                    "created_time": "1463154797", 
                    "from": {
                        "full_name": "Kuliner Kere", 
                        "id": "1936338325", 
                        "profile_picture": "https://instagram.fcgk4-2.fna.fbcdn.net/t51.2885-19/s150x150/15258972_1704593896521255_3904786636898041856_a.jpg", 
                        "username": "kulinerkere"
                    }, 
                    "id": "17856911701046320", 
                    "text": "@aminullah_lubis tegarkere :))"
                }, 
                {
                    "created_time": "1463194516", 
                    "from": {
                        "full_name": "Tegar M K P", 
                        "id": "3176222716", 
                        "profile_picture": "https://instagram.fcgk4-2.fna.fbcdn.net/t51.2885-19/s150x150/14269253_198476207237335_1735316193_a.jpg", 
                        "username": "tegarmkp"
                    }, 
                    "id": "17856925855046320", 
                    "text": "Terima kasih @kulinerkere yg udh mau minjemin kamerany ke saya yg kere ini"
                }, 
                {
                    "created_time": "1463197289", 
                    "from": {
                        "full_name": "Kuliner Kere", 
                        "id": "1936338325", 
                        "profile_picture": "https://instagram.fcgk4-2.fna.fbcdn.net/t51.2885-19/s150x150/15258972_1704593896521255_3904786636898041856_a.jpg", 
                        "username": "kulinerkere"
                    }, 
                    "id": "17856926719046320", 
                    "text": "@tegarmkp siapalah saya ini.mz. Kalo makan juga selalu sederhana"
                }, 
                {
                    "created_time": "1471053113", 
                    "from": {
                        "full_name": "محمد رضا فحلفي", 
                        "id": "311959338", 
                        "profile_picture": "https://instagram.fcgk4-2.fna.fbcdn.net/t51.2885-19/s150x150/21434044_586386001752001_3045786017987559424_a.jpg", 
                        "username": "rezapahlvi"
                    }, 
                    "id": "17860595170046320", 
                    "text": "folbek suhu"
                }
            ]
        }, 
        "created_time": "1463153791", 
        "id": "1249347012926273117_3176222716", 
        "images": {
            "low_resolution": {
                "height": 213, 
                "url": "https://instagram.fcgk4-2.fna.fbcdn.net/t51.2885-15/s320x320/e35/13188129_565400243620503_738812987_n.jpg", 
                "width": 320
            }, 
            "standard_resolution": {
                "height": 426, 
                "url": "https://instagram.fcgk4-2.fna.fbcdn.net/t51.2885-15/s640x640/sh0.08/e35/13188129_565400243620503_738812987_n.jpg", 
                "width": 640
            }, 
            "thumbnail": {
                "height": 150, 
                "url": "https://instagram.fcgk4-2.fna.fbcdn.net/t51.2885-15/s150x150/e35/c180.0.720.720/13188129_565400243620503_738812987_n.jpg", 
                "width": 150
            }
        }, 
        "likes": {
            "count": 22, 
            "data": [
                {
                    "full_name": "Mutya Yuliandari", 
                    "id": "1445367732", 
                    "profile_picture": "https://instagram.fcgk4-2.fna.fbcdn.net/t51.2885-19/s150x150/18948240_1395630630518949_6101490150548701184_a.jpg", 
                    "username": "mutyayuliandari"
                }, 
                {
                    "full_name": "レ ギ な", 
                    "id": "32638574", 
                    "profile_picture": "https://instagram.fcgk4-2.fna.fbcdn.net/t51.2885-19/s150x150/20759471_134937327022433_5059521506762031104_a.jpg", 
                    "username": "reginarda"
                }, 
                {
                    "full_name": "M. Alif Akbar Pranagara, S.H.", 
                    "id": "1069259336", 
                    "profile_picture": "https://instagram.fcgk4-2.fna.fbcdn.net/t51.2885-19/s150x150/16585737_186808575138998_4603578936943706112_a.jpg", 
                    "username": "pranagara1"
                }, 
                {
                    "full_name": "Afifah Astarini", 
                    "id": "308481519", 
                    "profile_picture": "https://instagram.fcgk4-2.fna.fbcdn.net/t51.2885-19/s150x150/20066662_1408562392584987_1515066953662726144_a.jpg", 
                    "username": "_afifafif"
                }
            ]
        }, 
        "link": "https://www.instagram.com/p/BFWkn0qqnZd/", 
        "location": {
            "name": "Paskal Food Market - Paskal Hyper Square Bandung"
        }, 
        "tags": [], 
        "type": "image", 
        "urls": [
            "https://instagram.fcgk4-2.fna.fbcdn.net/t51.2885-15/sh0.08/e35/13188129_565400243620503_738812987_n.jpg"
        ], 
        "user": {
            "full_name": "Tegar M K P", 
            "id": "3176222716", 
            "profile_picture": "https://instagram.fcgk4-2.fna.fbcdn.net/t51.2885-19/s150x150/14269253_198476207237335_1735316193_a.jpg", 
            "username": "tegarmkp"
        }
    }
]